{
  "experiment": "c-theorem",
  "results": {
    "0.5B": {
      "avg_c": [
        0.1997,
        31.9307,
        68.1956,
        89.2908,
        126.8926,
        154.7536,
        185.8359,
        223.5336,
        227.5307,
        251.7814,
        259.6917,
        286.8042,
        259.2249,
        312.0092,
        344.7978,
        422.5964,
        532.9778,
        797.9281,
        1147.7632,
        1472.0982,
        1935.3972,
        3065.0117,
        5461.845,
        6133.2851,
        83649.5032
      ],
      "avg_ee": [
        6.7978,
        6.7762,
        6.658,
        6.6459,
        6.2643,
        5.5688,
        5.2954,
        4.2454,
        4.9286,
        3.6564,
        3.4036,
        2.459,
        4.0882,
        2.1166,
        1.1363,
        1.0867,
        0.5653,
        0.0143,
        0.0057,
        0.0004,
        0.0,
        0.0,
        0.0,
        0.0,
        0.0
      ],
      "mono_frac": 0.0833,
      "c_uv": -4476.4953,
      "c_ir": 4476.695,
      "ratio_uv_ir": 0.0,
      "r2_fit": 0.0029,
      "c_theorem_holds": false
    },
    "1.5B": {
      "avg_c": [
        0.9204,
        426.746,
        715.2563,
        976.7435,
        1381.4997,
        1879.6994,
        1847.5947,
        2085.7928,
        2236.3869,
        2441.3553,
        2804.3651,
        3106.4228,
        3091.298,
        2962.8464,
        3330.7166,
        3601.569,
        3801.2314,
        4106.7817,
        4559.1812,
        5762.5405,
        7218.013,
        9174.9345,
        13877.8711,
        19724.5664,
        27800.1821,
        41833.646,
        59243.9219,
        94649.373,
        43566.2437
      ],
      "avg_ee": [
        7.3366,
        6.9631,
        5.671,
        4.2744,
        2.5168,
        1.4558,
        1.5028,
        1.1329,
        0.9379,
        0.9035,
        0.9315,
        0.8039,
        0.6458,
        0.6656,
        0.5888,
        0.436,
        0.1867,
        0.1832,
        0.1076,
        0.0301,
        0.0705,
        0.055,
        0.0305,
        0.0004,
        0.0,
        0.0,
        0.0,
        0.0,
        0.0006
      ],
      "mono_frac": 0.1607,
      "c_uv": -13149.3218,
      "c_ir": 13150.2421,
      "ratio_uv_ir": 0.0,
      "r2_fit": 0.013,
      "c_theorem_holds": false
    }
  }
}